tableshare/__init__.py
tableshare/crawltable/__init__.py
tableshare-1.1.5.dist-info/LICENSE
tableshare-1.1.5.dist-info/METADATA
tableshare-1.1.5.dist-info/WHEEL
tableshare-1.1.5.dist-info/top_level.txt
tableshare-1.1.5.dist-info/RECORD
